<?xml version="1.0" encoding="UTF-8" ?>
<!DOCTYPE mapper PUBLIC "-//mybatis.org//DTD Mapper 3.0//EN" "http://mybatis.org/dtd/mybatis-3-mapper.dtd" >
<mapper namespace="com.web.dao.TRolePermissionMapper" >
  <resultMap id="BaseResultMap" type="com.web.model.TRolePermission" >
    <!--
      WARNING - @mbggenerated
      This element is automatically generated by MyBatis Generator, do not modify.
    -->
    <id column="ID" property="id" jdbcType="INTEGER" />
    <result column="ROLE_ID" property="roleId" jdbcType="INTEGER" />
    <result column="PERMISSION_ID" property="permissionId" jdbcType="INTEGER" />
    <result column="AVAILABLE" property="available" jdbcType="VARCHAR" />
  </resultMap>
  <delete id="deleteByPrimaryKey" parameterType="java.lang.Integer" >
    <!--
      WARNING - @mbggenerated
      This element is automatically generated by MyBatis Generator, do not modify.
    -->
    delete from T_ROLE_PERMISSION
    where ID = #{id,jdbcType=INTEGER}
  </delete>
  <insert id="insert" parameterType="com.web.model.TRolePermission" >
    <!--
      WARNING - @mbggenerated
      This element is automatically generated by MyBatis Generator, do not modify.
    -->
    insert into T_ROLE_PERMISSION (ID, ROLE_ID, PERMISSION_ID, 
      AVAILABLE)
    values (#{id,jdbcType=INTEGER}, #{roleId,jdbcType=INTEGER}, #{permissionId,jdbcType=INTEGER}, 
      #{available,jdbcType=VARCHAR})
  </insert>
  <update id="updateByPrimaryKey" parameterType="com.web.model.TRolePermission" >
    <!--
      WARNING - @mbggenerated
      This element is automatically generated by MyBatis Generator, do not modify.
    -->
    update T_ROLE_PERMISSION
    set ROLE_ID = #{roleId,jdbcType=INTEGER},
      PERMISSION_ID = #{permissionId,jdbcType=INTEGER},
      AVAILABLE = #{available,jdbcType=VARCHAR}
    where ID = #{id,jdbcType=INTEGER}
  </update>
  <select id="selectByPrimaryKey" resultMap="BaseResultMap" parameterType="java.lang.Integer" >
    <!--
      WARNING - @mbggenerated
      This element is automatically generated by MyBatis Generator, do not modify.
    -->
    select ID, ROLE_ID, PERMISSION_ID, AVAILABLE
    from T_ROLE_PERMISSION
    where ID = #{id,jdbcType=INTEGER}
  </select>
  <select id="selectAll" resultMap="BaseResultMap" >
    <!--
      WARNING - @mbggenerated
      This element is automatically generated by MyBatis Generator, do not modify.
    -->
    select ID, ROLE_ID, PERMISSION_ID, AVAILABLE
    from T_ROLE_PERMISSION
  </select>
</mapper>